aldryn_snake/__init__.py
aldryn_snake/template_api.py
tests/__init__.py
tests/settings.py
tests/test_migrations.py
aldryn_snake-2.0.0.dist-info/LICENSE
aldryn_snake-2.0.0.dist-info/METADATA
aldryn_snake-2.0.0.dist-info/WHEEL
aldryn_snake-2.0.0.dist-info/top_level.txt
aldryn_snake-2.0.0.dist-info/RECORD
